measure_incremental_development/__init__.py
measure_incremental_development/compute.py
measure_incremental_development-1.0.1.dist-info/LICENSE.txt
measure_incremental_development-1.0.1.dist-info/METADATA
measure_incremental_development-1.0.1.dist-info/WHEEL
measure_incremental_development-1.0.1.dist-info/top_level.txt
measure_incremental_development-1.0.1.dist-info/RECORD
