Metadata-Version: 2.1
Name: measure-incremental-development
Version: 1.0.1
Summary: A Package to use the Measure of Incremental Development on sequences of student snapshots of code
Home-page: https://github.com/anshulshah99/measure-of-incremental-development
Author: Anshul Shah
Author-email: ayshah@ucsd.edu
Project-URL: Repository, https://github.com/anshulshah99/measure-of-incremental-development
Classifier: Programming Language :: Python :: 3
Classifier: License :: OSI Approved :: MIT License
Classifier: Operating System :: OS Independent
Requires-Python: >=3.6
License-File: LICENSE.txt
Requires-Dist: tokenizer
